oktools/__init__.py
oktools/build_exercise.py
oktools/check_ok_marks.py
oktools/check_pushed.sh
oktools/check_tests_total.py
oktools/cutils.py
oktools/delete_modified.sh
oktools/dir2exercise.py
oktools/grade_oknb.py
oktools/grade_plot_nbs.py
oktools/make_jh_link.py
oktools/makedir.py
oktools/makeq.py
oktools/ok_check_marks.py
oktools/okdir.py
oktools/okq.py
oktools/process_nb.py
oktools/write_plot_nbs.py
oktools/tests/test_build_exercise.py
oktools/tests/test_cutils.py
oktools/tests/test_dir2exercise.py
oktools/tests/test_grade_oknb.py
oktools/tests/data/_config.yml
oktools/tests/data/course.yml
oktools/tests/data/empty_dir/.gitignore
oktools/tests/data/exercise_dir/_config.yml
oktools/tests/data/three_girls/.ok_storage
oktools/tests/data/three_girls/.ok_storage.db
oktools/tests/data/three_girls/three_girls.Rmd
oktools/tests/data/three_girls/three_girls.ok
oktools/tests/data/three_girls/three_girls_solution_minus_15.Rmd
oktools/tests/data/three_girls/three_girls_template.Rmd
oktools/tests/data/three_girls/tests/__init__.py
oktools/tests/data/three_girls/tests/q_1_no_girls.py
oktools/tests/data/three_girls/tests/q_2_three_of_five.py
oktools/tests/data/three_girls/tests/q_3_three_or_fewer.py
oktools/tests/data/three_girls/tests/q_4_r_three_of_four.py
oktools-0.0.1a3.dist-info/entry_points.txt
oktools-0.0.1a3.dist-info/LICENSE
oktools-0.0.1a3.dist-info/WHEEL
oktools-0.0.1a3.dist-info/METADATA
oktools-0.0.1a3.dist-info/RECORD
