Metadata-Version: 2.1
Name: oktools
Version: 0.0.1a3
Summary: OKtools package
Home-page: https://github.com/matthew-brett/oktools
Author: Matthew Brett
Author-email: matthew.brett@gmail.com
Requires-Python: >=3.6
Classifier: License :: OSI Approved :: BSD License
Classifier: Programming Language :: Python :: 3
Requires-Dist: gradools
Requires-Dist: rmdex
Requires-Dist: rnbgrader>=0.2
